botree-0.4.1.dist-info/METADATA
botree-0.4.1.dist-info/WHEEL
botree-0.4.1.dist-info/licenses/LICENSE
botree/__init__.py
botree/core.py
botree/cost_explorer.py
botree/logs.py
botree/s3.py
botree/secrets_manager.py
botree-0.4.1.dist-info/RECORD
