Metadata-Version: 2.1
Name: botree
Version: 0.4.1
Summary: A friendly wrapper for boto3.
Author-Email: ericmiguel <eric.mrib@gmail.com>
License: MIT
Requires-Python: >=3.9
Requires-Dist: boto3>=1.28.10
Requires-Dist: boto3-stubs>=1.28.10
